stissplice/__init__.py
stissplice/splicer.py
stissplice/tools.py
stissplice-1.0.4.dist-info/LICENSE
stissplice-1.0.4.dist-info/METADATA
stissplice-1.0.4.dist-info/WHEEL
stissplice-1.0.4.dist-info/top_level.txt
stissplice-1.0.4.dist-info/RECORD
