Metadata-Version: 2.1
Name: stissplice
Version: 1.0.4
Summary: Splicer of STIS Echelle Spectra from Hubble Space Telescope
Home-page: https://github.com/ladsantos/stissplice
Author: Leonardo dos Santos
Author-email: ldsantos@stsci.edu
License: MIT
Classifier: Development Status :: 5 - Production/Stable
Classifier: Intended Audience :: Science/Research
Classifier: License :: OSI Approved :: MIT License
Classifier: Operating System :: OS Independent
Classifier: Programming Language :: Python
License-File: LICENSE
Requires-Dist: numpy
Requires-Dist: scipy
Requires-Dist: astropy
